{
  "required": true,
  "package": "dev.nathanpb.dml.mixin",
  "compatibilityLevel": "JAVA_8",
  "mixins": [
    "AbstractBlockAccessor",
    "BowItemMixin",
    "CrossbowItemMixin",
    "EndermanEntityMixin",
    "HungerManagerMixin",
    "ICraftingResultSlotMixin",
    "LivingEntityMixin",
    "LootTableInvoker",
    "PlayerEntityMixin",
    "ServerWorldMixin",
    "ShapelessRecipeAccessor",
    "SlotMixin",
    "SmithingTemplateItemAccessor",
    "WListPanelAccessor",
    "WorldMixin"
  ],
  "client": [
    "BakedModelManagerAccessor",
    "DrawContextAccessor",
    "HandledScreenAccessor"
  ],
  "injectors": {
    "defaultRequire": 1
  }
}
